powerprotect/__init__.py
powerprotect-0.1.0.dist-info/LICENSE
powerprotect-0.1.0.dist-info/METADATA
powerprotect-0.1.0.dist-info/WHEEL
powerprotect-0.1.0.dist-info/top_level.txt
powerprotect-0.1.0.dist-info/RECORD
