Metadata-Version: 2.1
Name: powerprotect
Version: 0.1.0
Summary: PowerProtect Python Class
Home-page: https://github.com/EMC-Underground/powerprotect
Author: Brad Soper
Author-email: bradley.soper@dell.com
License: UNKNOWN
Platform: UNKNOWN
Classifier: Programming Language :: Python :: 3
Classifier: License :: OSI Approved :: MIT License
Classifier: Operating System :: OS Independent
Requires-Python: >=3.6
